{
  "sections": {
    "hero": {
      "type": "section-hero",
      "blocks": {
        "9b00c4ed-c65e-4154-89e7-a6405a9cd70e": {
          "type": "text",
          "settings": {
            "richtext": "<p>This area is used to describe your store.<\/p>",
            "text_size": 6
          }
        }
      },
      "block_order": [
        "9b00c4ed-c65e-4154-89e7-a6405a9cd70e"
      ],
      "disabled": true,
      "settings": {
        "height": "use_screen_one_fifth",
        "overlay_opacity": 50,
        "overlay_color": "#000000",
        "enable_overlay_text": false,
        "content_width": 2000,
        "text_align": "align--middle-center",
        "text_color": "text--white",
        "color_bg": "hero__content--transparent",
        "width": "wrapper--none",
        "padding_top": 0,
        "padding_bottom": 0
      }
    },
    "main": {
      "type": "page",
      "settings": {
        "kicker": "",
        "kicker_size": 3,
        "show_title": false,
        "title_size": 8,
        "show_content": true,
        "content_size": 4,
        "align_text": "text-center",
        "text_color": "text--neutral",
        "bg": "palette--light bg--accent",
        "width": "wrapper--full",
        "padding_top": 36,
        "padding_bottom": 36
      }
    },
    "contact": {
      "type": "section-contact",
      "blocks": {
        "name": {
          "type": "text",
          "settings": {
            "title": "Full Name"
          }
        },
        "email": {
          "type": "email",
          "settings": {
            "title": "Email"
          }
        },
        "message": {
          "type": "body",
          "settings": {
            "title": "Message"
          }
        }
      },
      "block_order": [
        "name",
        "email",
        "message"
      ],
      "settings": {
        "title": "Contact us",
        "align_text": "text-left",
        "text_color": "text--neutral",
        "bg": "palette--light bg--accent",
        "width": "wrapper--narrow",
        "padding_top": 18,
        "padding_bottom": 36
      }
    },
    "faq": {
      "type": "section-faq",
      "blocks": {
        "faq-0": {
          "type": "text",
          "settings": {
            "title": "Frequently asked question",
            "content": "<p>Share details about your shipping policies, item returns, or customer service.<\/p>"
          }
        },
        "faq-1": {
          "type": "text",
          "settings": {
            "title": "Frequently asked question",
            "content": "<p>Share details about your shipping policies, item returns, or customer service.<\/p>"
          }
        },
        "faq-2": {
          "type": "text",
          "settings": {
            "title": "Frequently asked question",
            "content": "<p>Share details about your shipping policies, item returns, or customer service.<\/p>"
          }
        },
        "faq-3": {
          "type": "text",
          "settings": {
            "title": "Frequently asked question",
            "content": "<p>Share details about your shipping policies, item returns, or customer service.<\/p>"
          }
        }
      },
      "block_order": [
        "faq-0",
        "faq-1",
        "faq-2",
        "faq-3"
      ],
      "disabled": true,
      "settings": {
        "title": "",
        "title_align": "text-left",
        "title_size": 4,
        "heading_size": 5,
        "text_size": 5,
        "text_color": "text--neutral",
        "bg": "palette--light bg--neutral",
        "width": "wrapper",
        "padding_top": 36,
        "padding_bottom": 36
      }
    },
    "icons": {
      "type": "section-icons",
      "blocks": {
        "icons-0": {
          "type": "icon_block",
          "settings": {
            "icon_name": "icon-basket-return",
            "icon_color": "#aaaaaa",
            "title": "Free returns",
            "text": "<p>Returns within 30 days receive a full refund.<\/p>",
            "link_text": "",
            "link_url": ""
          }
        },
        "icons-1": {
          "type": "icon_block",
          "settings": {
            "icon_name": "icon-shipment-world",
            "icon_color": "#aaaaaa",
            "title": "Worldwide shipping",
            "text": "<p>Ship anywhere, rates available at checkout.<\/p>",
            "link_text": "",
            "link_url": ""
          }
        },
        "icons-2": {
          "type": "icon_block",
          "settings": {
            "icon_name": "icon-phone",
            "icon_color": "#aaaaaa",
            "title": "24\/7 support",
            "text": "<p>Call us anytime at 1(800) 555-1234.<\/p>",
            "link_text": "",
            "link_url": ""
          }
        }
      },
      "block_order": [
        "icons-0",
        "icons-1",
        "icons-2"
      ],
      "disabled": true,
      "settings": {
        "title": "",
        "bg": "palette--light bg--accent",
        "icon_size": "icon--medium",
        "icon_alignment": "icon--top",
        "layout": "grid--stacked",
        "align_text": "text-left",
        "width": "wrapper",
        "padding_top": 36,
        "padding_bottom": 36
      }
    }
  },
  "order": [
    "hero",
    "main",
    "contact",
    "faq",
    "icons"
  ]
}
